tacitpy/__init__.py
tacitpy-0.1.1.dist-info/LICENSE
tacitpy-0.1.1.dist-info/METADATA
tacitpy-0.1.1.dist-info/WHEEL
tacitpy-0.1.1.dist-info/top_level.txt
tacitpy-0.1.1.dist-info/RECORD
