Metadata-Version: 2.1
Name: tacitpy
Version: 0.1.1
Summary: Tacit programming for Python.
Home-page: https://git.sr.ht/~knutsen/tacitpy
Author: Samuel Knutsen
Author-email: samuel@knuten.co
License: UNKNOWN
Platform: UNKNOWN
Classifier: Programming Language :: Python :: 3
Classifier: License :: OSI Approved :: GNU General Public License v3 (GPLv3)
Classifier: Operating System :: OS Independent
Requires-Python: >=3.2
